pygammon/__init__.py
pygammon/core.py
pygammon/exceptions.py
pygammon/structures.py
tests/__init__.py
tests/integration/__init__.py
tests/integration/helpers.py
tests/integration/test_game.py
tests/integration/test_run.py
tests/unit/__init__.py
tests/unit/test_game.py
tests/unit/test_run.py
pygammon-0.0.3.dist-info/LICENSE
pygammon-0.0.3.dist-info/METADATA
pygammon-0.0.3.dist-info/WHEEL
pygammon-0.0.3.dist-info/top_level.txt
pygammon-0.0.3.dist-info/RECORD
